youtube_crawler/__init__.py
youtube_crawler/_base_crawler.py
youtube_crawler/comment_crawler.py
youtube_crawler/video_info_crawler.py
youtube_crawler/browser_agent/__init__.py
youtube_crawler/browser_agent/_agent.py
youtube_crawler/config/__init__.py
youtube_crawler/config/filter_enum.py
youtube_crawler/dao/__init__.py
youtube_crawler/dao/pojo/__init__.py
youtube_crawler/dao/pojo/_video_comment.py
youtube_crawler/dao/pojo/_video_info.py
youtube_crawler/page_parser/__init__.py
youtube_crawler/page_parser/_main.py
youtube_crawler/page_parser/modules/__init__.py
youtube_crawler/page_parser/modules/_base_page_parser.py
youtube_crawler/page_parser/modules/url_parser.py
youtube_crawler/page_parser/modules/video_comment_parser.py
youtube_crawler/page_parser/modules/video_info_parser.py
youtube_crawler/page_parser/selectors/__init__.py
youtube_crawler/page_parser/selectors/common.py
youtube_crawler/page_parser/selectors/search_result_page.py
youtube_crawl-0.1.dist-info/LICENCE
youtube_crawl-0.1.dist-info/METADATA
youtube_crawl-0.1.dist-info/WHEEL
youtube_crawl-0.1.dist-info/top_level.txt
youtube_crawl-0.1.dist-info/RECORD
