Metadata-Version: 2.1
Name: youtube-crawl
Version: 0.1
Summary: A powerful, asynchronous web crawler designed specifically for YouTube.
Home-page: https://github.com/stevieflyer/youtube_crawler
Author: Steve Flyer
Author-email: steveflyer7@gmail.com
License-File: LICENCE
Requires-Dist: gembox
Requires-Dist: pyppeteer
Requires-Dist: zephyrion
